MANIFEST.in
setup.py
django_dummyimage.egg-info/PKG-INFO
django_dummyimage.egg-info/SOURCES.txt
django_dummyimage.egg-info/dependency_links.txt
django_dummyimage.egg-info/not-zip-safe
django_dummyimage.egg-info/requires.txt
django_dummyimage.egg-info/top_level.txt
dummyimage/__init__.py
dummyimage/forms.py
dummyimage/models.py
dummyimage/settings.py
dummyimage/tests.py
dummyimage/urls.py
dummyimage/views.py
dummyimage/fonts/DroidSans.ttf
dummyimage/templatetags/__init__.py
dummyimage/templatetags/dummyimage_tags.py