Metadata-Version: 1.1
Name: django-dummyimage
Version: 0.1.1
Summary: Dynamic Dummy Image Generator For Django!
Home-page: https://github.com/darkrho/django-dummyimage
Author: Rolando Espinoza La fuente
Author-email: darkrho@gmail.com
License: BSD
Platform: UNKNOWN
Classifier: Programming Language :: Python
Classifier: Framework :: Django
Classifier: Development Status :: 4 - Beta
Classifier: Intended Audience :: Developers
